simpledorff/__init__.py
simpledorff/data_transforms.py
simpledorff/metrics.py
simpledorff/simpledorff.py
simpledorff-0.0.2.dist-info/LICENSE
simpledorff-0.0.2.dist-info/METADATA
simpledorff-0.0.2.dist-info/WHEEL
simpledorff-0.0.2.dist-info/top_level.txt
simpledorff-0.0.2.dist-info/RECORD
