Metadata-Version: 2.1
Name: simpledorff
Version: 0.0.2
Summary: Calculate Krippendorff's Alpha on any DataFrame
Home-page: https://github.com/lighttag/simpledorff
Author: Tal Perry
Author-email: tal@lighttag.io
License: UNKNOWN
Platform: UNKNOWN
Classifier: Programming Language :: Python :: 3
Classifier: License :: OSI Approved :: MIT License
Classifier: Operating System :: OS Independent
